{
 "㐀": "丘",
 "㐅": "五",
 "㐫": "凶",
 "㐮": "襄",
 "㐯": "庸",
 "㐱": "鬒",
 "㐵": "儒",
 "㑁": "𠭴",
 "㑄": "侮",
 "㑝": "𢙱",
 "㒋": "廝",
 "㒞": "儶",
 "㒰": "全",
 "㒲": "財",
 "㒷": "興",
 "㓮": "彫",
 "㓷": "劓",
 "㗖": "啖",
 "㘅": "啣",
 "㘽": "栽",
 "㚣": "姣",
 "㛛": "娠",
 "㝛": "宿",
 "㞐": "居",
 "㟗": "豳",
 "㠯": "以",
 "㠶": "帆",
 "㡿": "斥",
 "㣺": "心",
 "㣼": "忍",
 "㤵": "慈",
 "㥃": "悶",
 "㥵": "慁",
 "㦧": "憯",
 "㧖": "扼",
 "㧜": "擸",
 "㨗": "捷",
 "㨼": "撂",
 "㩁": "搉",
 "㩅": "㨨",
 "㩜": "攬",
 "㪅": "更",
 "㪯": "舉",
 "㬅": "曼",
 "㬱": "朁",
 "㭨": "椰",
 "㯃": "漆",
 "㯭": "櫓",
 "㳄": "涎",
 "㷉": "熨",
 "㷻": "煳",
 "㽣": "域",
 "䀋": "鹽",
 "䃉": "珉",
 "䄃": "殃",
 "䆋": "秋",
 "䈇": "罩",
 "䉵": "籑",
 "䋲": "繩",
 "䌫": "纜",
 "䒒": "苕",
 "䔛": "檾",
 "䖈": "虐",
 "䖍": "虔",
 "䖏": "處",
 "䖟": "蝱",
 "䘑": "脉",
 "䘚": "卒",
 "䙝": "褺",
 "䛡": "話",
 "䛻": "誘",
 "䞓": "赬",
 "䥀": "捵",
 "䥷": "㔍",
 "䨘": "霰",
 "䪿": "囟",
 "䬡": "翥",
 "䭾": "馱",
 "䯻": "髻",
 "䰗": "鬮",
 "䱇": "鱓",
 "䱷": "漁",
 "䱽": "鯧",
 "䵑": "䵒",
 "与": "與",
 "东": "東",
 "両": "兩",
 "丢": "丟",
 "两": "兩",
 "义": "義",
 "乔": "喬",
 "乚": "隱",
 "乱": "亂",
 "乹": "乾",
 "亁": "乾",
 "争": "爭",
 "亊": "事",
 "亗": "歲",
 "亲": "榛",
 "亻": "人",
 "亼": "集",
 "亾": "亡",
 "从": "從",
 "仼": "任",
 "仾": "低",
 "会": "會",
 "伱": "你",
 "伷": "冑",
 "余": "予",
 "作": "𠈨",
 "侎": "敉",
 "侶": "侣",
 "俞": "兪",
 "俻": "備",
 "個": "个",
 "倐": "倏",
 "倣": "仿",
 "値": "值",
 "偁": "稱",
 "偃": "㫃",
 "偐": "贋",
 "偸": "偷",
 "偺": "咱",
 "傁": "叟",
 "僊": "仙",
 "僱": "雇",
 "儍": "傻",
 "儛": "㒇",
 "儻": "倘",
 "兌": "兑",
 "兎": "兔",
 "兦": "亡",
 "兹": "玆",
 "冄": "冉",
 "冋": "冂",
 "冗": "宂",
 "冩": "寫",
 "冰": "冫",
 "冱": "沍",
 "冲": "沖",
 "决": "決",
 "况": "況",
 "凂": "浼",
 "凄": "淒",
 "凈": "淨",
 "凉": "涼",
 "减": "減",
 "凑": "湊",
 "凛": "懔",
 "凢": "凡",
 "凣": "凡",
 "処": "處",
 "凴": "憑",
 "凾": "函",
 "刂": "刀",
 "刄": "刃",
 "刋": "刊",
 "刘": "劉",
 "刦": "劫",
 "刧": "劫",
 "刪": "删",
 "别": "別",
 "刷": "㕞",
 "刼": "劫",
 "剁": "刴",
 "剦": "閹",
 "剪": "翦",
 "創": "刅",
 "剷": "剗",
 "劄": "剳",
 "劒": "劍",
 "劔": "劎",
 "劝": "勸",
 "办": "辦",
 "効": "效",
 "勄": "敏",
 "勑": "倈",
 "勗": "勖",
 "勛": "勳",
 "勻": "匀",
 "勽": "㲒",
 "匃": "丐",
 "包": "勹",
 "匘": "腦",
 "匳": "奩",
 "千": "仟",
 "卄": "廿",
 "卍": "万",
 "協": "勰",
 "单": "單",
 "卧": "臥",
 "卩": "㔾",
 "卭": "卬",
 "即": "卽",
 "却": "卻",
 "历": "厲",
 "厠": "廁",
 "厦": "廈",
 "厨": "廚",
 "厪": "廑",
 "厮": "廝",
 "厰": "廠",
 "叁": "三",
 "叅": "參",
 "双": "雙",
 "变": "變",
 "叙": "敍",
 "叜": "叟",
 "叠": "疊",
 "叡": "睿",
 "叴": "厹",
 "吊": "弔",
 "同": "仝",
 "吶": "訥",
 "吿": "告",
 "呉": "吳",
 "呌": "叫",
 "呑": "吞",
 "呡": "吻",
 "咊": "和",
 "咏": "詠",
 "咒": "呪",
 "咤": "吒",
 "咲": "笑",
 "咿": "吚",
 "哂": "吲",
 "响": "響",
 "哶": "咩",
 "唚": "吣",
 "唫": "吟",
 "啍": "吨",
 "啕": "咷",
 "啗": "啖",
 "啟": "啓",
 "喆": "哲",
 "喨": "哴",
 "喫": "吃",
 "喭": "唁",
 "嗁": "啼",
 "嗒": "㗳",
 "嗞": "咨",
 "嘈": "䜊",
 "嘱": "囑",
 "嘴": "咀",
 "嘷": "嗥",
 "噉": "啖",
 "噏": "吸",
 "噐": "器",
 "噪": "喿",
 "噴": "呠",
 "嚎": "嗥",
 "嚥": "咽",
 "嚳": "俈",
 "囘": "回",
 "囪": "囱",
 "囬": "回",
 "园": "刓",
 "囯": "國",
 "圅": "函",
 "圕": "圖",
 "圞": "圝",
 "坌": "坋",
 "坛": "壇",
 "坭": "泥",
 "坯": "坏",
 "坰": "冂",
 "坵": "丘",
 "垜": "垛",
 "埳": "坎",
 "埼": "㟢",
 "堃": "坤",
 "堘": "塍",
 "堙": "垔",
 "堦": "階",
 "塐": "塑",
 "塔": "㙮",
 "塟": "葬",
 "塩": "鹽",
 "塲": "場",
 "墰": "壜",
 "墳": "坆",
 "墻": "廧",
 "壍": "塹",
 "壎": "塤",
 "壐": "璽",
 "壩": "垻",
 "壳": "㱿",
 "壹": "一",
 "夀": "壽",
 "夅": "降",
 "変": "變",
 "夠": "够",
 "夣": "夢",
 "夯": "䂫",
 "奎": "㚝",
 "奞": "㚝",
 "她": "他",
 "妤": "伃",
 "妬": "妒",
 "妳": "奶",
 "姉": "姊",
 "姗": "姍",
 "姙": "妊",
 "姥": "姆",
 "娩": "㝃",
 "娬": "嫵",
 "婀": "娿",
 "婣": "姻",
 "婿": "壻",
 "媍": "婦",
 "嫛": "嫕",
 "嫩": "媆",
 "嫻": "嫺",
 "嬭": "奶",
 "嬷": "嫫",
 "孃": "娘",
 "孼": "孽",
 "孾": "嬰",
 "它": "佗",
 "宐": "宜",
 "宝": "寶",
 "宻": "密",
 "宼": "寇",
 "寃": "冤",
 "寍": "寧",
 "寗": "甯",
 "寜": "寕",
 "實": "寔",
 "寳": "寶",
 "对": "對",
 "寿": "壽",
 "尀": "叵",
 "尅": "剋",
 "尒": "爾",
 "尔": "爾",
 "尗": "叔",
 "尣": "尢",
 "尩": "㑌",
 "尷": "尲",
 "尻": "䯌",
 "屆": "届",
 "屍": "尸",
 "屜": "屉",
 "属": "屬",
 "岀": "出",
 "岁": "歲",
 "岩": "巖",
 "峩": "峨",
 "峰": "峯",
 "崎": "㟢",
 "崖": "厓",
 "崗": "岡",
 "崙": "侖",
 "崧": "嵩",
 "崪": "崒",
 "嵗": "歲",
 "嵜": "㟢",
 "嵠": "谿",
 "嶃": "磛",
 "嶇": "㠊",
 "巉": "嶄",
 "川": "巛",
 "帀": "匝",
 "帋": "紙",
 "帒": "袋",
 "帬": "裙",
 "帮": "幫",
 "幇": "幫",
 "幑": "㫎",
 "幙": "幕",
 "并": "並",
 "幷": "並",
 "幸": "倖",
 "幺": "么",
 "庅": "麽",
 "床": "牀",
 "庙": "廟",
 "庬": "厖",
 "廀": "廋",
 "廌": "豸",
 "廐": "厩",
 "廵": "巡",
 "廸": "迪",
 "廹": "迫",
 "廻": "回",
 "廼": "乃",
 "开": "幵",
 "弈": "奕",
 "弌": "一",
 "弍": "二",
 "強": "强",
 "彀": "够",
 "彊": "强",
 "彑": "彐",
 "归": "歸",
 "彸": "伀",
 "徃": "往",
 "徑": "俓",
 "徠": "倈",
 "徤": "健",
 "徬": "彷",
 "徭": "傜",
 "忄": "心",
 "忤": "啎",
 "怱": "匆",
 "恊": "勰",
 "恋": "戀",
 "恍": "怳",
 "恒": "恆",
 "恠": "怪",
 "恡": "吝",
 "恤": "卹",
 "悅": "悦",
 "悊": "哲",
 "悋": "吝",
 "悤": "匆",
 "悳": "德",
 "惕": "悐",
 "惧": "懼",
 "惩": "懲",
 "惪": "德",
 "惽": "惛",
 "愉": "愈",
 "愧": "媿",
 "愽": "博",
 "慂": "恿",
 "慍": "愠",
 "慚": "慙",
 "慞": "傽",
 "慷": "忼",
 "慽": "慼",
 "憇": "憩",
 "憙": "喜",
 "憫": "愍",
 "懁": "悁",
 "懟": "憝",
 "懣": "悶",
 "懫": "懥",
 "懵": "懜",
 "懷": "怀",
 "戯": "戲",
 "戱": "戲",
 "戹": "厄",
 "扊": "扅",
 "扌": "手",
 "执": "執",
 "扵": "于",
 "抝": "拗",
 "报": "報",
 "抿": "㨉",
 "拓": "托",
 "拕": "拖",
 "拯": "抍",
 "拿": "拏",
 "挐": "拏",
 "挱": "挲",
 "挷": "搒",
 "捌": "八",
 "捍": "扞",
 "捼": "挼",
 "掃": "埽",
 "掛": "挂",
 "掬": "匊",
 "揑": "捏",
 "揜": "掩",
 "揫": "揪",
 "揶": "捓",
 "搃": "總",
 "搖": "摇",
 "搤": "扼",
 "搪": "傏",
 "搬": "搫",
 "搯": "掏",
 "携": "攜",
 "摁": "恩",
 "摒": "拼",
 "摠": "總",
 "摣": "揸",
 "撆": "撇",
 "撍": "揝",
 "撐": "撑",
 "撘": "搭",
 "撟": "嬌",
 "撦": "扯",
 "撫": "捬",
 "撲": "扑",
 "撳": "搇",
 "擊": "撽",
 "擒": "捦",
 "擔": "担",
 "擗": "劈",
 "擡": "抬",
 "擣": "搗",
 "擥": "攬",
 "擧": "舉",
 "擿": "擲",
 "攀": "扳",
 "攅": "攢",
 "攋": "揦",
 "攩": "擋",
 "攪": "搞",
 "攮": "擃",
 "攵": "攴",
 "收": "㧃",
 "敁": "掂",
 "敎": "教",
 "敗": "䢙",
 "敘": "敍",
 "敦": "惇",
 "敪": "敠",
 "敷": "尃",
 "斆": "斅",
 "斈": "學",
 "斋": "齋",
 "斌": "彬",
 "斚": "斝",
 "斞": "庾",
 "断": "斷",
 "斲": "㓸",
 "於": "于",
 "斾": "旆",
 "旈": "旒",
 "旉": "尃",
 "旗": "旂",
 "旘": "幟",
 "旛": "幡",
 "时": "時",
 "旹": "時",
 "昒": "㫚",
 "昝": "喒",
 "昪": "忭",
 "昬": "昏",
 "昷": "𥁕",
 "昻": "昂",
 "晋": "晉",
 "晒": "曬",
 "晳": "晰",
 "暋": "敃",
 "暎": "映",
 "暱": "昵",
 "曆": "厤",
 "曡": "疊",
 "朙": "明",
 "朝": "晁",
 "朢": "望",
 "朶": "朵",
 "杇": "圬",
 "条": "條",
 "来": "來",
 "杰": "傑",
 "杷": "朳",
 "枏": "楠",
 "枬": "楠",
 "枱": "儓",
 "柂": "杝",
 "某": "厶",
 "柒": "七",
 "柰": "奈",
 "柹": "枾",
 "査": "查",
 "栁": "柳",
 "栖": "棲",
 "栢": "柏",
 "桼": "漆",
 "梦": "夢",
 "梨": "棃",
 "梲": "棳",
 "棅": "柄",
 "棊": "棋",
 "棕": "椶",
 "棹": "桌",
 "椀": "盌",
 "楂": "揸",
 "楞": "棱",
 "楦": "楥",
 "榢": "架",
 "榧": "棐",
 "槌": "棰",
 "槑": "梅",
 "槓": "杠",
 "槖": "橐",
 "槨": "椁",
 "槩": "㮣",
 "槪": "㮣",
 "槹": "𣓌",
 "樊": "棥",
 "樐": "櫓",
 "樑": "梁",
 "樷": "叢",
 "樸": "朴",
 "樻": "匱",
 "樽": "墫",
 "橊": "榴",
 "橓": "蕣",
 "橜": "橛",
 "機": "机",
 "檁": "标",
 "檉": "柳",
 "檝": "楫",
 "檟": "榎",
 "檯": "儓",
 "檳": "梹",
 "櫃": "匱",
 "櫈": "凳",
 "櫌": "耰",
 "櫝": "匵",
 "櫳": "㰍",
 "櫾": "柚",
 "欓": "檔",
 "欝": "鬱",
 "欞": "櫺",
 "欢": "懽",
 "欣": "忻",
 "欬": "咳",
 "欲": "慾",
 "欵": "款",
 "欸": "唉",
 "欹": "猗",
 "欼": "啜",
 "歎": "嘆",
 "歕": "呠",
 "歗": "嘯",
 "歠": "啜",
 "歡": "懽",
 "歳": "歲",
 "歺": "歹",
 "歿": "殁",
 "殂": "𣨐",
 "殉": "侚",
 "殳": "杸",
 "殼": "㱿",
 "毘": "毗",
 "毡": "氈",
 "毧": "㲓",
 "氊": "氈",
 "氥": "氙",
 "氭": "氡",
 "氵": "水",
 "氷": "冫",
 "汚": "汙",
 "污": "汙",
 "沉": "沈",
 "沲": "沱",
 "沸": "㵒",
 "泛": "汎",
 "泪": "淚",
 "洞": "峒",
 "洤": "泉",
 "洩": "泄",
 "洿": "汙",
 "涕": "䶏",
 "涶": "唾",
 "淆": "殽",
 "淫": "婬",
 "渫": "泄",
 "渰": "淹",
 "湧": "涌",
 "湻": "淳",
 "湼": "涅",
 "溉": "摡",
 "準": "准",
 "溫": "温",
 "溯": "㴑",
 "溺": "氼",
 "滙": "匯",
 "滺": "悠",
 "漰": "淜",
 "潜": "潛",
 "潝": "㴔",
 "潣": "浼",
 "潨": "漎",
 "澁": "澀",
 "澈": "徹",
 "澣": "浣",
 "澷": "漫",
 "澹": "淡",
 "濇": "澀",
 "濕": "溼",
 "濬": "浚",
 "濵": "濱",
 "濶": "闊",
 "濿": "砅",
 "瀁": "漾",
 "瀒": "澀",
 "瀕": "濱",
 "灑": "洒",
 "灘": "潬",
 "灬": "火",
 "灶": "竈",
 "灾": "災",
 "炁": "氣",
 "炉": "爐",
 "炰": "炮",
 "点": "點",
 "為": "爲",
 "烕": "滅",
 "烖": "災",
 "烘": "灴",
 "烜": "晅",
 "烟": "完",
 "烱": "炯",
 "無": "橆",
 "煑": "煮",
 "煖": "暖",
 "煙": "完",
 "煠": "炸",
 "照": "炤",
 "煬": "烊",
 "熈": "熙",
 "燄": "焰",
 "燈": "灯",
 "燐": "㷠",
 "燭": "烛",
 "燺": "熇",
 "燻": "熏",
 "燿": "曜",
 "爪": "㕚",
 "爫": "㕚",
 "牆": "廧",
 "版": "板",
 "牋": "箋",
 "牜": "牛",
 "牠": "他",
 "犁": "犂",
 "犇": "奔",
 "犭": "犬",
 "犲": "豺",
 "狥": "侚",
 "独": "獨",
 "狵": "尨",
 "狻": "䝜",
 "猇": "唬",
 "猨": "猿",
 "猪": "豬",
 "献": "獻",
 "猶": "犹",
 "獃": "呆",
 "獠": "䝤",
 "獧": "狷",
 "玁": "獫",
 "玄": "伭",
 "玅": "妙",
 "玖": "九",
 "玫": "玟",
 "珎": "珍",
 "珪": "圭",
 "瑇": "玳",
 "瑠": "琉",
 "瑯": "琅",
 "璿": "璇",
 "瓈": "璃",
 "瓟": "匏",
 "甕": "瓮",
 "甖": "罃",
 "甞": "嘗",
 "甬": "埇",
 "町": "圢",
 "画": "畫",
 "甿": "氓",
 "畄": "留",
 "畆": "畝",
 "畎": "甽",
 "畧": "略",
 "畱": "留",
 "畵": "畫",
 "疃": "畽",
 "疆": "畺",
 "疋": "匹",
 "疎": "疏",
 "痄": "𤶙",
 "痴": "癡",
 "痺": "痹",
 "痼": "㽽",
 "痾": "疴",
 "瘂": "啞",
 "瘶": "嗽",
 "瘺": "瘻",
 "癉": "疸",
 "癒": "瘉",
 "癢": "痒",
 "癲": "瘨",
 "百": "佰",
 "皂": "皁",
 "皃": "貌",
 "皎": "㿟",
 "皜": "暠",
 "皝": "皓",
 "皡": "皞",
 "皥": "皞",
 "皦": "㿟",
 "皰": "疱",
 "皷": "鼓",
 "盃": "杯",
 "盇": "盍",
 "盖": "蓋",
 "盗": "盜",
 "盙": "簠",
 "盡": "尽",
 "盭": "盩",
 "真": "眞",
 "眦": "眥",
 "眾": "衆",
 "睏": "困",
 "睫": "䀹",
 "睾": "皋",
 "瞪": "瞠",
 "瞬": "䀢",
 "瞷": "瞯",
 "瞹": "曖",
 "瞿": "䀠",
 "矁": "瞅",
 "矋": "矖",
 "矙": "瞰",
 "砇": "珉",
 "研": "揅",
 "砠": "岨",
 "砥": "厎",
 "砦": "寨",
 "砲": "炮",
 "硜": "䃘",
 "硤": "唊",
 "碁": "棋",
 "碍": "㝵",
 "碔": "珷",
 "碕": "㟢",
 "碗": "盌",
 "碪": "砧",
 "碯": "瑙",
 "碰": "掽",
 "磁": "瓷",
 "磇": "砒",
 "磚": "甎",
 "磡": "墈",
 "磥": "磊",
 "磪": "崔",
 "磴": "嶝",
 "磵": "澗",
 "磽": "墝",
 "礙": "㝵",
 "礮": "炮",
 "礶": "罐",
 "礻": "示",
 "礼": "禮",
 "祐": "佑",
 "禀": "稟",
 "禱": "禂",
 "禴": "礿",
 "禿": "秃",
 "秇": "埶",
 "秌": "秋",
 "秐": "耘",
 "秘": "祕",
 "稈": "秆",
 "稉": "秔",
 "稊": "䄺",
 "稘": "朞",
 "稚": "䕌",
 "稜": "棱",
 "稬": "糯",
 "稭": "秸",
 "稿": "槀",
 "穌": "甦",
 "穤": "糯",
 "穩": "㒚",
 "穪": "稱",
 "穫": "檴",
 "窃": "竊",
 "窓": "牕",
 "窖": "窌",
 "窗": "牕",
 "窰": "窯",
 "窴": "塡",
 "窶": "寠",
 "窻": "牕",
 "竆": "窮",
 "竉": "䆔",
 "竒": "奇",
 "竚": "佇",
 "竝": "並",
 "竢": "俟",
 "竪": "豎",
 "笔": "筆",
 "笨": "㤒",
 "筍": "笋",
 "筏": "栰",
 "箇": "个",
 "箒": "帚",
 "算": "筭",
 "箛": "箍",
 "箠": "捶",
 "管": "筦",
 "箸": "筯",
 "篋": "匧",
 "篠": "筱",
 "篦": "笓",
 "篪": "箎",
 "篴": "笛",
 "篺": "棑",
 "簁": "篩",
 "簒": "篡",
 "簕": "竻",
 "簛": "篩",
 "簨": "栒",
 "簫": "燒",
 "簷": "檐",
 "簻": "檛",
 "簾": "𢅖",
 "籃": "箖",
 "籄": "簣",
 "籼": "秈",
 "粃": "秕",
 "粦": "㷠",
 "粧": "妝",
 "粮": "糧",
 "粳": "秔",
 "粵": "粤",
 "糇": "餱",
 "糉": "粽",
 "糓": "穀",
 "糙": "㿷",
 "糠": "穅",
 "糡": "糨",
 "糤": "饊",
 "糰": "䊜",
 "糶": "條",
 "糹": "糸",
 "糾": "糺",
 "紮": "扎",
 "紹": "佋",
 "絃": "弦",
 "絚": "緪",
 "絪": "氤",
 "綂": "統",
 "綑": "捆",
 "綠": "氯",
 "綢": "紬",
 "綳": "繃",
 "綻": "䘺",
 "綿": "緜",
 "線": "綫",
 "緤": "紲",
 "緲": "眇",
 "縁": "緣",
 "縆": "緪",
 "縐": "皺",
 "縚": "絛",
 "縟": "溽",
 "縯": "䌥",
 "繈": "繦",
 "繖": "傘",
 "繡": "綉",
 "繰": "繅",
 "繲": "挫",
 "纊": "絖",
 "纖": "砌",
 "缸": "堈",
 "缻": "缶",
 "缽": "鉢",
 "缾": "瓶",
 "罁": "堈",
 "罇": "墫",
 "罈": "壜",
 "罋": "瓮",
 "罌": "罃",
 "网": "罔",
 "罗": "羅",
 "置": "寘",
 "罵": "傌",
 "羃": "冪",
 "羗": "羌",
 "羙": "美",
 "群": "羣",
 "羨": "羡",
 "羮": "羹",
 "羶": "羴",
 "翅": "翄",
 "翱": "翺",
 "耀": "曜",
 "考": "攷",
 "耐": "耏",
 "耑": "專",
 "耔": "秄",
 "耗": "秏",
 "耜": "㭒",
 "耻": "恥",
 "耼": "聃",
 "聖": "圣",
 "聦": "聰",
 "聲": "声",
 "聽": "听",
 "肆": "四",
 "肈": "肇",
 "肧": "胚",
 "肬": "疣",
 "肱": "厷",
 "育": "毓",
 "肳": "吻",
 "胄": "冑",
 "胑": "肢",
 "胗": "疹",
 "胮": "肨",
 "胳": "肐",
 "胷": "匈",
 "胸": "匈",
 "脃": "脆",
 "脇": "脅",
 "脈": "脉",
 "脣": "唇",
 "脪": "㾙",
 "脹": "痮",
 "腫": "尰",
 "腳": "脚",
 "膆": "嗉",
 "膫": "膋",
 "膽": "胆",
 "臈": "腊",
 "臘": "腊",
 "臙": "胭",
 "臞": "癯",
 "臯": "皋",
 "臺": "台",
 "舀": "抌",
 "舊": "旧",
 "舓": "舐",
 "舖": "鋪",
 "舘": "館",
 "舵": "柁",
 "船": "舡",
 "艜": "舦",
 "艢": "檣",
 "艥": "楫",
 "艪": "櫓",
 "艶": "豔",
 "艹": "艸",
 "芒": "杧",
 "芔": "卉",
 "苢": "苡",
 "苤": "瞥",
 "茍": "苟",
 "茲": "玆",
 "荅": "答",
 "草": "艸",
 "荊": "荆",
 "荔": "栛",
 "荣": "榮",
 "莅": "涖",
 "莊": "庄",
 "莓": "苺",
 "莕": "荇",
 "莿": "朿",
 "菑": "災",
 "菓": "果",
 "菫": "堇",
 "菰": "菇",
 "菴": "庵",
 "萬": "万",
 "萲": "萱",
 "著": "着",
 "葚": "椹",
 "葢": "蓋",
 "蒞": "涖",
 "蒭": "芻",
 "蒸": "烝",
 "蓖": "萆",
 "蓧": "莜",
 "蓴": "蒓",
 "蓺": "埶",
 "蔔": "菔",
 "蔚": "嶎",
 "蔥": "葱",
 "蔭": "廕",
 "蕈": "菌",
 "蕋": "蕊",
 "蕎": "荍",
 "蕢": "簣",
 "蕤": "甤",
 "蕩": "偒",
 "薅": "茠",
 "薑": "葁",
 "薦": "荐",
 "藉": "耤",
 "藝": "埶",
 "藤": "籐",
 "藥": "葯",
 "藷": "薯",
 "蘆": "芦",
 "蘑": "藦",
 "蘖": "櫱",
 "蘞": "薟",
 "蘤": "花",
 "蘽": "藟",
 "虓": "唬",
 "虜": "擄",
 "號": "号",
 "虣": "暴",
 "虯": "虬",
 "虱": "蝨",
 "蚘": "痐",
 "蚤": "䖣",
 "蚦": "蚺",
 "蚪": "虬",
 "蛋": "疍",
 "蛌": "蛄",
 "蜝": "蜞",
 "蜡": "䄍",
 "蜫": "䖵",
 "蜹": "蚋",
 "蝇": "蠅",
 "蝟": "猬",
 "蝯": "猿",
 "蝶": "蜨",
 "螂": "蜋",
 "螆": "蚝",
 "螎": "融",
 "螮": "蝃",
 "螳": "螗",
 "螾": "蚓",
 "蟀": "蜶",
 "蟁": "蚊",
 "蟊": "蝥",
 "蟛": "蟚",
 "蟲": "虫",
 "蟺": "蟮",
 "蟻": "螘",
 "蠃": "螺",
 "蠍": "蝎",
 "蠏": "蟹",
 "蠧": "螙",
 "蠩": "蜍",
 "蠭": "蜂",
 "蠶": "蚕",
 "衂": "衄",
 "衅": "釁",
 "衇": "脉",
 "衛": "衞",
 "衤": "衣",
 "衿": "紟",
 "袞": "衮",
 "袠": "帙",
 "袴": "絝",
 "袵": "衽",
 "裌": "袷",
 "裠": "裙",
 "裡": "裏",
 "褃": "裉",
 "褏": "褎",
 "褒": "襃",
 "褓": "緥",
 "褟": "溻",
 "褧": "絅",
 "褱": "褢",
 "褲": "絝",
 "褵": "縭",
 "褻": "褺",
 "襁": "繦",
 "襍": "雜",
 "襖": "澳",
 "襝": "襜",
 "襢": "袒",
 "襪": "袜",
 "襮": "幞",
 "襯": "儭",
 "覇": "霸",
 "覊": "羈",
 "覌": "觀",
 "覐": "覺",
 "覔": "覓",
 "視": "眎",
 "覘": "䦓",
 "覩": "睹",
 "覷": "覰",
 "觔": "斤",
 "觕": "粗",
 "觜": "咀",
 "觝": "牴",
 "觧": "解",
 "觵": "觥",
 "訇": "渹",
 "託": "侂",
 "訠": "矧",
 "訴": "愬",
 "訽": "詬",
 "詋": "呪",
 "詧": "察",
 "詵": "侁",
 "詾": "訩",
 "誇": "夸",
 "誐": "哦",
 "誤": "悞",
 "誩": "競",
 "諁": "啜",
 "諊": "鞫",
 "諕": "唬",
 "諠": "喧",
 "諡": "謚",
 "諮": "咨",
 "諵": "喃",
 "諶": "訦",
 "謊": "詤",
 "謌": "歌",
 "謱": "嘍",
 "譁": "嘩",
 "譈": "憝",
 "證": "証",
 "譌": "訛",
 "譎": "憰",
 "譐": "噂",
 "譙": "誚",
 "譚": "談",
 "警": "儆",
 "譭": "䛼",
 "讁": "謫",
 "讌": "宴",
 "讍": "諤",
 "讎": "仇",
 "讐": "仇",
 "讘": "囁",
 "豆": "荳",
 "豇": "䜶",
 "豋": "登",
 "豓": "豔",
 "豚": "豘",
 "豜": "豣",
 "豝": "羓",
 "豵": "䝋",
 "豻": "犴",
 "貍": "狸",
 "貓": "猫",
 "貛": "獾",
 "貭": "質",
 "貳": "二",
 "賅": "侅",
 "賍": "贓",
 "賔": "賓",
 "賛": "贊",
 "賫": "齎",
 "賬": "帳",
 "賸": "剩",
 "贃": "賺",
 "贐": "賮",
 "贒": "賢",
 "贗": "贋",
 "贜": "贓",
 "趂": "趁",
 "趋": "趨",
 "趕": "赶",
 "跙": "趄",
 "跡": "迹",
 "跳": "趒",
 "跺": "跥",
 "踪": "蹤",
 "踭": "㬹",
 "踴": "踊",
 "踵": "歱",
 "踹": "跴",
 "踽": "偊",
 "蹋": "踏",
 "蹌": "牄",
 "蹏": "蹄",
 "蹝": "屣",
 "蹟": "迹",
 "蹠": "跖",
 "蹢": "豴",
 "蹵": "蹴",
 "蹻": "蹺",
 "躁": "趮",
 "躅": "䠱",
 "躍": "趯",
 "躗": "躛",
 "躚": "蹮",
 "躧": "屣",
 "躭": "眈",
 "躲": "躱",
 "躳": "躬",
 "躶": "裸",
 "躷": "矮",
 "軄": "職",
 "軆": "体",
 "軰": "輩",
 "輙": "輒",
 "輝": "煇",
 "輭": "軟",
 "轆": "樚",
 "轕": "輵",
 "轗": "㙳",
 "轝": "輿",
 "辞": "辭",
 "辠": "罪",
 "辢": "辣",
 "辤": "辭",
 "辯": "辨",
 "農": "莀",
 "辶": "辵",
 "边": "邊",
 "过": "過",
 "迊": "匝",
 "这": "這",
 "迩": "邇",
 "迯": "逃",
 "迺": "乃",
 "迻": "移",
 "逓": "遞",
 "逮": "迨",
 "週": "周",
 "逷": "逖",
 "逼": "偪",
 "逾": "踰",
 "遍": "徧",
 "遜": "愻",
 "遡": "泝",
 "遭": "蹧",
 "遶": "繞",
 "遷": "迁",
 "還": "还",
 "邅": "㣶",
 "邠": "豳",
 "邨": "村",
 "郁": "喐",
 "郤": "郄",
 "郷": "鄉",
 "鄔": "塢",
 "鄕": "鄉",
 "鄹": "郰",
 "酧": "酬",
 "醇": "䣩",
 "醡": "榨",
 "醩": "糟",
 "醫": "医",
 "醻": "酬",
 "野": "埜",
 "釐": "厘",
 "釒": "金",
 "針": "箴",
 "鈀": "耙",
 "鈎": "鉤",
 "鉈": "砣",
 "鉋": "刨",
 "鉗": "鉆",
 "鉛": "鈆",
 "鉞": "戉",
 "銁": "鈞",
 "銕": "鉄",
 "銲": "釬",
 "鋤": "鉏",
 "鍉": "匙",
 "鍛": "煅",
 "鍜": "煆",
 "鍫": "鍬",
 "鍼": "箴",
 "鎋": "轄",
 "鎌": "鐮",
 "鎒": "耨",
 "鎔": "熔",
 "鎙": "槊",
 "鎚": "錘",
 "鎻": "鎖",
 "鏁": "鎖",
 "鏐": "鎏",
 "鏽": "銹",
 "鐀": "匱",
 "鐫": "鋑",
 "鐵": "鉄",
 "鐶": "鍰",
 "鑒": "鑑",
 "鑛": "礦",
 "鑢": "䥨",
 "鑣": "鏢",
 "鑴": "鋑",
 "鑽": "鉆",
 "閆": "閻",
 "閒": "間",
 "閙": "鬧",
 "関": "𨶹",
 "门": "門",
 "阝": "阜",
 "阡": "仟",
 "阬": "坑",
 "阱": "穽",
 "阳": "氜",
 "阴": "陰",
 "阸": "阨",
 "陁": "陀",
 "陗": "峭",
 "陜": "狹",
 "陡": "阧",
 "陭": "㟢",
 "陶": "匋",
 "陻": "垔",
 "陼": "渚",
 "陽": "氜",
 "隂": "陰",
 "隄": "堤",
 "隈": "渨",
 "隍": "堭",
 "隕": "磒",
 "隖": "塢",
 "隝": "塢",
 "隠": "隐",
 "隣": "鄰",
 "隤": "墤",
 "隮": "躋",
 "隲": "騭",
 "隷": "隸",
 "难": "難",
 "雋": "隽",
 "雍": "邕",
 "雕": "彫",
 "雝": "廱",
 "雞": "鷄",
 "雷": "𤴐",
 "霜": "孀",
 "霢": "霡",
 "霥": "濛",
 "霶": "雱",
 "靀": "濛",
 "靈": "灵",
 "靝": "天",
 "靦": "覥",
 "鞀": "鼗",
 "鞉": "鼗",
 "鞙": "琄",
 "鞦": "鞧",
 "鞲": "韝",
 "鞴": "絥",
 "鞵": "鞋",
 "鞹": "鞟",
 "鞽": "橇",
 "鞾": "靴",
 "韁": "繮",
 "韂": "䩞",
 "韌": "肕",
 "韒": "鞘",
 "韜": "弢",
 "韮": "韭",
 "韵": "韻",
 "須": "湏",
 "預": "豫",
 "頤": "頣",
 "頫": "俯",
 "頮": "靧",
 "頴": "穎",
 "頼": "賴",
 "顋": "腮",
 "額": "頟",
 "顕": "顯",
 "顖": "囟",
 "願": "愿",
 "顥": "皓",
 "顦": "憔",
 "顧": "頋",
 "顰": "嚬",
 "颮": "猋",
 "颼": "䬒",
 "飇": "猋",
 "飠": "食",
 "飤": "飼",
 "飪": "䏕",
 "餂": "舔",
 "餐": "飡",
 "餙": "飾",
 "餚": "肴",
 "餜": "䴹",
 "餟": "醊",
 "餠": "餅",
 "餧": "喂",
 "餫": "餛",
 "餵": "諉",
 "餹": "糖",
 "餻": "糕",
 "饇": "飫",
 "饈": "䐰",
 "饋": "匱",
 "饌": "籑",
 "饍": "膳",
 "饑": "飢",
 "饕": "叨",
 "饘": "飦",
 "饞": "嚵",
 "饟": "餉",
 "馘": "聝",
 "馩": "馚",
 "馭": "御",
 "馿": "驢",
 "駦": "騰",
 "駪": "侁",
 "駮": "駁",
 "騈": "駢",
 "騌": "騣",
 "騐": "驗",
 "騗": "騙",
 "騘": "驄",
 "驅": "敺",
 "驘": "騾",
 "骴": "胔",
 "骻": "胯",
 "骽": "腿",
 "骾": "挭",
 "髃": "腢",
 "體": "体",
 "髕": "臏",
 "髗": "顱",
 "髙": "高",
 "髣": "彷",
 "鬀": "剃",
 "鬂": "鬢",
 "鬅": "髼",
 "鬣": "巤",
 "鬦": "鬥",
 "鬨": "閧",
 "鬪": "鬥",
 "鬬": "鬥",
 "鬭": "鬥",
 "魏": "巍",
 "魙": "聻",
 "鯁": "挭",
 "鯊": "魦",
 "鯗": "鮝",
 "鯷": "鮧",
 "鰌": "魷",
 "鰕": "蝦",
 "鰩": "魟",
 "鱑": "鰉",
 "鱔": "鱓",
 "鱠": "膾",
 "鱷": "鰐",
 "鱻": "鮮",
 "鳮": "鷄",
 "鴃": "鵙",
 "鴆": "酖",
 "鴈": "雁",
 "鴝": "朐",
 "鴞": "梟",
 "鵜": "鴺",
 "鵞": "鵝",
 "鵻": "隼",
 "鶃": "鶂",
 "鶵": "雛",
 "鶽": "隼",
 "鷃": "鴳",
 "鷩": "氅",
 "鸎": "鶯",
 "鸜": "朐",
 "鹻": "堿",
 "鹼": "堿",
 "麄": "粗",
 "麐": "麟",
 "麕": "麇",
 "麞": "獐",
 "麤": "粗",
 "麰": "牟",
 "麴": "麯",
 "麵": "麪",
 "麻": "蔴",
 "麼": "麽",
 "黏": "粘",
 "默": "嘿",
 "鼃": "蛙",
 "鼄": "蛛",
 "鼇": "鰲",
 "鼈": "鱉",
 "鼏": "冪",
 "鼔": "鼓",
 "齅": "嗅",
 "齊": "亝",
 "齦": "啃",
 "齧": "囓",
 "齩": "咬",
 "齶": "腭",
 "龎": "龐",
 "龒": "龍",
 "龓": "䪊",
 "龝": "秋",
 "龠": "籥",
 "龡": "吹",
 "龢": "和",
 "龤": "諧",
 "龥": "籲",
 "﨑": "㟢",
 "礼": "禮",
 "𠂝": "匝",
 "𠆌": "庸",
 "𠊧": "併",
 "𠔃": "兮",
 "𠕄": "凹",
 "𠖥": "寵",
 "𠗦": "憑",
 "𠚹": "芟",
 "𠜎": "鏾",
 "𠜼": "掐",
 "𠞰": "剿",
 "𠦌": "卌",
 "𠯗": "咂",
 "𠲿": "欶",
 "𠸺": "𠱘",
 "𠼮": "𠱓",
 "𡅈": "嚹",
 "𡈙": "囮",
 "𡑞": "隧",
 "𡒃": "隩",
 "𡚁": "弊",
 "𡜱": "嫉",
 "𡨴": "寧",
 "𡱆": "屬",
 "𡻕": "歲",
 "𢂑": "拭",
 "𢅏": "㡘",
 "𢆞": "䄯",
 "𢍺": "弋",
 "𢐧": "檠",
 "𢕐": "渹",
 "𢙢": "恐",
 "𢜫": "惺",
 "𢠳": "憋",
 "𢠵": "惝",
 "𢥠": "悚",
 "𢭆": "抽",
 "𢯱": "搜",
 "𢲷": "搜",
 "𢳆": "摮",
 "𢳜": "漇",
 "𢶑": "𢸣",
 "𢶣": "㩹",
 "𣁚": "𣁟",
 "𣄈": "㫎",
 "𣇀": "晡",
 "𣉞": "暠",
 "𣔼": "竿",
 "𣳨": "𠂤",
 "𣽽": "潸",
 "𤆍": "赤",
 "𤍠": "熱",
 "𤎱": "臇",
 "𤑕": "熏",
 "𤕪": "爿",
 "𤕭": "將",
 "𤕯": "漿",
 "𤢕": "斁",
 "𤢪": "獵",
 "𤦏": "璁",
 "𤧚": "璁",
 "𤮨": "礱",
 "𥂁": "鹽",
 "𥅾": "䚎",
 "𥈟": "瞍",
 "𥋟": "䂀",
 "𥐘": "石",
 "𥐞": "硭",
 "𥓿": "砣",
 "𥔎": "㟢",
 "𥜌": "澳",
 "𥝢": "利",
 "𥫱": "囤",
 "𥵚": "竻",
 "𦀇": "經",
 "𦂳": "緊",
 "𦍩": "羖",
 "𦕒": "䦓",
 "𦙵": "腕",
 "𦙶": "股",
 "𦚓": "胓",
 "𦞣": "臊",
 "𦢌": "殰",
 "𦷝": "芻",
 "𦽊": "驊",
 "𧀹": "蔗",
 "𧋍": "蜇",
 "𧌓": "蛗",
 "𧐅": "蛆",
 "𧐢": "蠔",
 "𧘂": "衝",
 "𧞪": "𧙀",
 "𧩙": "誕",
 "𧬨": "噦",
 "𧰊": "磌",
 "𧴯": "孭",
 "𧶶": "販",
 "𧿹": "拇",
 "𨃟": "𨃞",
 "𨉉": "𨈚",
 "𨍳": "軺",
 "𨑒": "徒",
 "𨢥": "䤍",
 "𨣦": "藇",
 "𨸚": "級",
 "𨸬": "陣",
 "𨻲": "罅",
 "𩋘": "鞋",
 "𩔖": "類",
 "𩔗": "類",
 "𩠑": "頂",
 "𩢲": "駛",
 "𩦢": "虞",
 "𩨘": "肐",
 "𩯭": "鬓",
 "𪔂": "鼎",
 "𪖙": "齁",
 "𪪝": "邕",
 "𫢊": "錢",
 "𫬛": "𫫲",
 "𫽮": "擋",
 "𬑔": "衆",
 "𬑡": "瞅",
 "𭀖": "厘"
}